docs/source/conf.py
examples/ged/aids_simgnn.py
grt_env/Lib/site-packages/_virtualenv.py
grt_env/Lib/site-packages/_distutils_hack/__init__.py
grt_env/Lib/site-packages/_distutils_hack/override.py
grt_env/Lib/site-packages/pip/__init__.py
grt_env/Lib/site-packages/pip/__main__.py
grt_env/Lib/site-packages/pip/__pip-runner__.py
grt_env/Lib/site-packages/pip/_internal/__init__.py
grt_env/Lib/site-packages/pip/_internal/build_env.py
grt_env/Lib/site-packages/pip/_internal/cache.py
grt_env/Lib/site-packages/pip/_internal/configuration.py
grt_env/Lib/site-packages/pip/_internal/exceptions.py
grt_env/Lib/site-packages/pip/_internal/main.py
grt_env/Lib/site-packages/pip/_internal/pyproject.py
grt_env/Lib/site-packages/pip/_internal/self_outdated_check.py
grt_env/Lib/site-packages/pip/_internal/wheel_builder.py
grt_env/Lib/site-packages/pip/_internal/cli/__init__.py
grt_env/Lib/site-packages/pip/_internal/cli/autocompletion.py
grt_env/Lib/site-packages/pip/_internal/cli/base_command.py
grt_env/Lib/site-packages/pip/_internal/cli/cmdoptions.py
grt_env/Lib/site-packages/pip/_internal/cli/command_context.py
grt_env/Lib/site-packages/pip/_internal/cli/main.py
grt_env/Lib/site-packages/pip/_internal/cli/main_parser.py
grt_env/Lib/site-packages/pip/_internal/cli/parser.py
grt_env/Lib/site-packages/pip/_internal/cli/progress_bars.py
grt_env/Lib/site-packages/pip/_internal/cli/req_command.py
grt_env/Lib/site-packages/pip/_internal/cli/spinners.py
grt_env/Lib/site-packages/pip/_internal/cli/status_codes.py
grt_env/Lib/site-packages/pip/_internal/commands/__init__.py
grt_env/Lib/site-packages/pip/_internal/commands/cache.py
grt_env/Lib/site-packages/pip/_internal/commands/check.py
grt_env/Lib/site-packages/pip/_internal/commands/completion.py
grt_env/Lib/site-packages/pip/_internal/commands/configuration.py
grt_env/Lib/site-packages/pip/_internal/commands/debug.py
grt_env/Lib/site-packages/pip/_internal/commands/download.py
grt_env/Lib/site-packages/pip/_internal/commands/freeze.py
graph_retrieval_toolkit-0.0.1.dist-info/METADATA
graph_retrieval_toolkit-0.0.1.dist-info/WHEEL
graph_retrieval_toolkit-0.0.1.dist-info/licenses/LICENSE
graph_retrieval_toolkit-0.0.1.dist-info/RECORD
