Metadata-Version: 2.1
Name: graph_retrieval_toolkit
Version: 0.0.1
Project-URL: Homepage, https://github.com/grtorg/graphretrievaltoolkit
Project-URL: Bug Tracker, https://github.com/grtorg/graphretrievaltoolkit/issues
Author-email: Sanidhya Anand <sanidhya.anand@iitb.ac.in>, Kunind Sahu <kunind444@gmail.com>
License-File: LICENSE
Classifier: License :: OSI Approved :: MIT License
Classifier: Operating System :: OS Independent
Classifier: Programming Language :: Python :: 3
Requires-Python: >=3.7
